{
  "metadata": {
    "coordinate_format": "normalized",
    "last_updated": "2025-03-30 15:10:28",
    "original_image_size": "1799x2347"
  },
  "machines": {
    "F42": {
      "screens": {
        "Setting": [
          {
            "name": "Do_day_khuon_setting",
            "coordinates": [
              0.14446318156267565,
              0.23706530958439356,
              0.21079258010118043,
              0.2586938083121289
            ]
          },
          {
            "name": "Alpha_setting",
            "coordinates": [
              0.32490163012928613,
              0.23791348600508905,
              0.38167509836987074,
              0.2586938083121289
            ]
          },
          {
            "name": "Vtri_khuon",
            "coordinates": [
              0.8465430016863407,
              0.16327396098388464,
              0.9494097807757167,
              0.18999151823579305
            ]
          },
          {
            "name": "Do_day_khuon_hien_tai",
            "coordinates": [
              0.8482293423271501,
              0.19083969465648856,
              0.9482855536818438,
              0.2171331636980492
            ]
          },
          {
            "name": "Vtri_bp_day",
            "coordinates": [
              0.8673412029229904,
              0.22264631043256997,
              0.9482855536818438,
              0.2480916030534351
            ]
          },
          {
            "name": "Momen_bp_day",
            "coordinates": [
              0.849353569421023,
              0.2506361323155216,
              0.9106239460370995,
              0.27438507209499574
            ]
          },
          {
            "name": "Luc_kep_setting",
            "coordinates": [
              0.31197301854974707,
              0.6751484308736218,
              0.38167509836987074,
              0.6980491942324003
            ]
          },
          {
            "name": "Gioi_han_mo_khuon",
            "coordinates": [
              0.32490163012928613,
              0.8125530110262935,
              0.38167509836987074,
              0.8363019508057676
            ]
          },
          {
            "name": "Luc_kep",
            "coordinates": [
              0.897133220910624,
              0.5589482612383376,
              0.9505340078695896,
              0.5860899067005937
            ]
          },
          {
            "name": "Momen_kep",
            "coordinates": [
              0.896008993816751,
              0.5962680237489398,
              0.9494097807757167,
              0.6259541984732825
            ]
          },
          {
            "name": "Gioi_han_ap_suat_tiep_xuc",
            "coordinates": [
              0.48903878583473864,
              0.779050042408821,
              0.5334457560427206,
              0.8006785411365565
            ]
          }
        ],
        "Temp": [
          {
            "name": "Vung_5",
            "coordinates": [
              0.3516483516483517,
              0.22955583229555832,
              0.4153846153846154,
              0.25072644250726445
            ]
          },
          {
            "name": "Vung_4",
            "coordinates": [
              0.4318681318681319,
              0.22748028227480283,
              0.4956043956043956,
              0.25072644250726445
            ]
          },
          {
            "name": "Vung_3",
            "coordinates": [
              0.5087912087912088,
              0.228310502283105,
              0.5747252747252747,
              0.25072644250726445
            ]
          },
          {
            "name": "Vung_2",
            "coordinates": [
              0.5884615384615385,
              0.228310502283105,
              0.6554945054945055,
              0.25072644250726445
            ]
          },
          {
            "name": "Vung_1",
            "coordinates": [
              0.6675824175824175,
              0.228310502283105,
              0.7335164835164835,
              0.25072644250726445
            ]
          },
          {
            "name": "Nhiet_do_nuoc",
            "coordinates": [
              0.8313186813186814,
              0.228310502283105,
              0.8901098901098901,
              0.25072644250726445
            ]
          },
          {
            "name": "Z5_cai_dat",
            "coordinates": [
              0.34505494505494505,
              0.37069323370693236,
              0.41098901098901097,
              0.39227895392278955
            ]
          },
          {
            "name": "Z4_cai_dat",
            "coordinates": [
              0.4225274725274725,
              0.37193856371938566,
              0.48846153846153845,
              0.3914487339144873
            ]
          },
          {
            "name": "Z3_cai_dat",
            "coordinates": [
              0.5005494505494505,
              0.37193856371938566,
              0.5664835164835165,
              0.39227895392278955
            ]
          },
          {
            "name": "Z2_cai_dat",
            "coordinates": [
              0.578021978021978,
              0.37069323370693236,
              0.6461538461538462,
              0.3906185139061851
            ]
          },
          {
            "name": "Z1_cai_dat",
            "coordinates": [
              0.6554945054945055,
              0.37069323370693236,
              0.7241758241758242,
              0.39227895392278955
            ]
          },
          {
            "name": "Nuoc_cai_dat",
            "coordinates": [
              0.8241758241758241,
              0.36820257368202575,
              0.8879120879120879,
              0.39227895392278955
            ]
          },
          {
            "name": "Z5_xa_nhua",
            "coordinates": [
              0.34505494505494505,
              0.40473225404732255,
              0.41098901098901097,
              0.4259028642590286
            ]
          },
          {
            "name": "Z4_xa_nhua",
            "coordinates": [
              0.4225274725274725,
              0.40390203403902036,
              0.48846153846153845,
              0.42673308426733086
            ]
          },
          {
            "name": "Z3_xa_nhua",
            "coordinates": [
              0.5027472527472527,
              0.40473225404732255,
              0.5664835164835165,
              0.42673308426733086
            ]
          },
          {
            "name": "Z2_xa_nhua",
            "coordinates": [
              0.5791208791208792,
              0.40473225404732255,
              0.6450549450549451,
              0.42673308426733086
            ]
          },
          {
            "name": "Z1_xa_nhua",
            "coordinates": [
              0.6571428571428571,
              0.40473225404732255,
              0.7230769230769231,
              0.42507264425072644
            ]
          },
          {
            "name": "Z5_2_nhiet_do_nhac_nho",
            "coordinates": [
              0.41098901098901097,
              0.43918638439186386,
              0.4989010989010989,
              0.46077210460772106
            ]
          },
          {
            "name": "Z1_nhiet_do_nhac_nho",
            "coordinates": [
              0.6582417582417582,
              0.4383561643835616,
              0.7230769230769231,
              0.45994188459941887
            ]
          },
          {
            "name": "Z5_khoang_theo_doi",
            "coordinates": [
              0.3516483516483517,
              0.47239518472395187,
              0.41098901098901097,
              0.49522623495226237
            ]
          },
          {
            "name": "Z4_khoang_theo_doi",
            "coordinates": [
              0.42747252747252745,
              0.47405562474055624,
              0.48846153846153845,
              0.49356579493565794
            ]
          },
          {
            "name": "Z3_khoang_theo_doi",
            "coordinates": [
              0.506043956043956,
              0.47322540473225405,
              0.5664835164835165,
              0.4943960149439601
            ]
          },
          {
            "name": "Z2_khoang_theo_doi",
            "coordinates": [
              0.5813186813186814,
              0.47322540473225405,
              0.643956043956044,
              0.49356579493565794
            ]
          },
          {
            "name": "Z1_khoang_theo_doi",
            "coordinates": [
              0.6582417582417582,
              0.47405562474055624,
              0.7230769230769231,
              0.49356579493565794
            ]
          },
          {
            "name": "Nuoc_khoang_theo_doi",
            "coordinates": [
              0.8241758241758241,
              0.4715649647156496,
              0.8868131868131868,
              0.49356579493565794
            ]
          },
          {
            "name": "Z5_A",
            "coordinates": [
              0.3598901098901099,
              0.5454545454545454,
              0.42142857142857143,
              0.5711913657119136
            ]
          },
          {
            "name": "Z4_A",
            "coordinates": [
              0.4401098901098901,
              0.54337899543379,
              0.4967032967032967,
              0.5691158156911582
            ]
          },
          {
            "name": "Z3_A",
            "coordinates": [
              0.5170329670329671,
              0.5442092154420921,
              0.578021978021978,
              0.5703611457036114
            ]
          },
          {
            "name": "Z2_A",
            "coordinates": [
              0.5912087912087912,
              0.5454545454545454,
              0.6554945054945055,
              0.5691158156911582
            ]
          },
          {
            "name": "Z1_A",
            "coordinates": [
              0.6758241758241759,
              0.5454545454545454,
              0.7324175824175824,
              0.568285595682856
            ]
          },
          {
            "name": "Z5_Cai_dat_ngat",
            "coordinates": [
              0.3659340659340659,
              0.5799086757990868,
              0.41098901098901097,
              0.6014943960149439
            ]
          },
          {
            "name": "Z4_cai_dat_ngat",
            "coordinates": [
              0.44395604395604393,
              0.5799086757990868,
              0.48846153846153845,
              0.6014943960149439
            ]
          },
          {
            "name": "Z3_cai_dat_ngat",
            "coordinates": [
              0.5214285714285715,
              0.5807388958073889,
              0.5675824175824176,
              0.6014943960149439
            ]
          },
          {
            "name": "Z2_cai_dat_ngat",
            "coordinates": [
              0.5967032967032967,
              0.5807388958073889,
              0.6472527472527473,
              0.6014943960149439
            ]
          },
          {
            "name": "Z1_cai_dat_ngat",
            "coordinates": [
              0.676923076923077,
              0.5799086757990868,
              0.7252747252747253,
              0.6014943960149439
            ]
          },
          {
            "name": "Ngan_khoi_dong_nguoi",
            "coordinates": [
              0.8252747252747252,
              0.7222914072229141,
              0.8593406593406593,
              0.742631797426318
            ]
          }
        ],
        "Plasticizer": [
          {
            "name": "Vtri_khuon",
            "coordinates": [
              0.17398554752640355,
              0.293992330634853,
              0.26292384658143414,
              0.31529612270984236
            ]
          },
          {
            "name": "Dday_khuon",
            "coordinates": [
              0.17287381878821567,
              0.3174265019173413,
              0.26181211784324626,
              0.34000852151683
            ]
          },
          {
            "name": "Vtri_EJ",
            "coordinates": [
              0.4774874930516954,
              0.29569663400085217,
              0.5403001667593107,
              0.3170004260758415
            ]
          },
          {
            "name": "Luc_kep",
            "coordinates": [
              0.4841689827682045,
              0.3204090328078398,
              0.5403001667593107,
              0.34171282488282917
            ]
          },
          {
            "name": "Chu_ki",
            "coordinates": [
              0.6931628682601445,
              0.17554324669791224,
              0.7670928293496387,
              0.19769919045590115
            ]
          },
          {
            "name": "Dien",
            "coordinates": [
              0.6920511395219566,
              0.19812526629740093,
              0.7676486937187327,
              0.22113336173838943
            ]
          },
          {
            "name": "D_lg",
            "coordinates": [
              0.6931628682601445,
              0.2224115892628888,
              0.7698721511951084,
              0.2449936088623775
            ]
          },
          {
            "name": "Giu_con_lai",
            "coordinates": [
              0.7059477487493052,
              0.2475500639113762,
              0.7676486937187327,
              0.2684277801448658
            ]
          },
          {
            "name": "L_mat_con_lai",
            "coordinates": [
              0.6987326292384658,
              0.2714103110353643,
              0.7676486937187327,
              0.2910097997443545
            ]
          },
          {
            "name": "Tvit",
            "coordinates": [
              0.6770539188438021,
              0.2948444823178526,
              0.7520844913841023,
              0.31614827439284193
            ]
          },
          {
            "name": "Xoay_truc_vit",
            "coordinates": [
              0.6853974430239022,
              0.31998295696634,
              0.7520844913841023,
              0.3387302939923306
            ]
          },
          {
            "name": "Trc_dien",
            "coordinates": [
              0.8709416342412452,
              0.17003008095440987,
              0.9566425792106726,
              0.1989774179804005
            ]
          },
          {
            "name": "V_P",
            "coordinates": [
              0.8827181767648694,
              0.1928121005538986,
              0.9577543079488605,
              0.22113336173838943
            ]
          },
          {
            "name": "Dem",
            "coordinates": [
              0.8857181767648694,
              0.2173941201533873,
              0.9577543079488605,
              0.24414145717937794
            ]
          },
          {
            "name": "Kthuc_giu",
            "coordinates": [
              0.8927181767648694,
              0.2488282914358756,
              0.9566425792106726,
              0.26927993182786536
            ]
          },
          {
            "name": "Dinh_dien",
            "coordinates": [
              0.8499444135630906,
              0.26326246271836385,
              0.9371873262923847,
              0.2927141031103536
            ]
          },
          {
            "name": "Toan_dinh",
            "coordinates": [
              0.8588326848249028,
              0.2948444823178526,
              0.9382990550305725,
              0.31529612270984236
            ]
          },
          {
            "name": "Ap_suat_ep",
            "coordinates": [
              0.869047804335742,
              0.3151308052833404,
              0.9410783768760422,
              0.3395824456753302
            ]
          },
          {
            "name": "Ghan_do_giu",
            "coordinates": [
              0.25680933852140075,
              0.38645078824030676,
              0.3129516397998888,
              0.4073285044737963
            ]
          },
          {
            "name": "T2_thgian",
            "coordinates": [
              0.2556976097832129,
              0.4414145717937793,
              0.3129516397998888,
              0.46186621218576907
            ]
          },
          {
            "name": "T1_thgian",
            "coordinates": [
              0.33351862145636463,
              0.44056242011077973,
              0.3885491939966648,
              0.4610140605027695
            ]
          },
          {
            "name": "T4_ap_suat",
            "coordinates": [
              0.12284602556976097,
              0.46910950149126546,
              0.1584213451917732,
              0.4895611418832552
            ]
          },
          {
            "name": "T3_ap_suat",
            "coordinates": [
              0.19955530850472486,
              0.4708138048572646,
              0.23513062812673707,
              0.4904132935662548
            ]
          },
          {
            "name": "T2_ap_suat",
            "coordinates": [
              0.26292384658143414,
              0.469961653174265,
              0.3129516397998888,
              0.4904132935662548
            ]
          },
          {
            "name": "T1_ap_suat",
            "coordinates": [
              0.33852140077821014,
              0.4708138048572646,
              0.3885491939966648,
              0.4895611418832552
            ]
          },
          {
            "name": "Flash",
            "coordinates": [
              0.42301278488048916,
              0.5023434171282488,
              0.49305169538632576,
              0.5244993608862377
            ]
          },
          {
            "name": "Ghan_thgian_dien",
            "coordinates": [
              0.6842690383546415,
              0.38645078824030676,
              0.7498610339077265,
              0.4073285044737963
            ]
          },
          {
            "name": "V_P_Vtri",
            "coordinates": [
              0.5647581989994441,
              0.4414145717937793,
              0.6297943301834352,
              0.46186621218576907
            ]
          },
          {
            "name": "T4_Vtri",
            "coordinates": [
              0.6370205669816564,
              0.4414145717937793,
              0.7059477487493052,
              0.4610140605027695
            ]
          },
          {
            "name": "T3_Vtri",
            "coordinates": [
              0.7065091717620901,
              0.4414145717937793,
              0.782657031684269,
              0.46186621218576907
            ]
          },
          {
            "name": "V_P_Tdo",
            "coordinates": [
              0.5925514174541412,
              0.46910950149126546,
              0.6475819899944414,
              0.4904132935662548
            ]
          },
          {
            "name": "T4_Tdo",
            "coordinates": [
              0.669260700389105,
              0.4686834256497657,
              0.7237354085603113,
              0.4904132935662548
            ]
          },
          {
            "name": "T3_Tdo",
            "coordinates": [
              0.7392996108949417,
              0.46910950149126546,
              0.7982212340188994,
              0.4895611418832552
            ]
          },
          {
            "name": "T2_Tdo",
            "coordinates": [
              0.8143413007226237,
              0.4686834256497657,
              0.8721511951083936,
              0.4904132935662548
            ]
          },
          {
            "name": "T1_Tdo",
            "coordinates": [
              0.8999444135630906,
              0.46910950149126546,
              0.9460811561978877,
              0.4904132935662548
            ]
          },
          {
            "name": "Ap_suat_tong",
            "coordinates": [
              0.7242912729294052,
              0.49637835534725183,
              0.7954419121734296,
              0.5189603749467405
            ]
          },
          {
            "name": "T_hoan_ph_dl",
            "coordinates": [
              0.09005002779321845,
              0.5743502343417128,
              0.13285158421345192,
              0.5952279505752024
            ]
          },
          {
            "name": "L-mat",
            "coordinates": [
              0.08060033351862146,
              0.6233489561141883,
              0.13340744858254586,
              0.6442266723476778
            ]
          },
          {
            "name": "Quang",
            "coordinates": [
              0.09116175653140633,
              0.6714955262036643,
              0.13340744858254586,
              0.6927993182786536
            ]
          },
          {
            "name": "Keo_ve_vtri",
            "coordinates": [
              0.28237909949972206,
              0.593949723050703,
              0.33740967204002226,
              0.6135492117596932
            ]
          },
          {
            "name": "Keo_ve_tdo",
            "coordinates": [
              0.28237909949972206,
              0.6207925010651896,
              0.33852140077821014,
              0.6420962931401789
            ]
          },
          {
            "name": "T2_Vtri",
            "coordinates": [
              0.5758754863813229,
              0.5913932680017043,
              0.6436909394107838,
              0.6135492117596932
            ]
          },
          {
            "name": "T2_Ap_sau",
            "coordinates": [
              0.6064480266814897,
              0.6195142735406902,
              0.6425792106725959,
              0.6429484448231785
            ]
          },
          {
            "name": "T2_xoay",
            "coordinates": [
              0.594774874930517,
              0.6489135066041756,
              0.6436909394107838,
              0.6702172986791649
            ]
          },
          {
            "name": "Het_Vtri",
            "coordinates": [
              0.6515847693162868,
              0.5913932680017043,
              0.7215119510839355,
              0.6135492117596932
            ]
          },
          {
            "name": "Het_Ap_sau",
            "coordinates": [
              0.6820455808782657,
              0.6207925010651896,
              0.7204002223457476,
              0.6408180656156796
            ]
          },
          {
            "name": "Het_xoay",
            "coordinates": [
              0.6714841578654808,
              0.648061354921176,
              0.7204002223457476,
              0.6706433745206647
            ]
          },
          {
            "name": "Keo_ve+Vtri",
            "coordinates": [
              0.8338021122846026,
              0.5913932680017043,
              0.8988326848249028,
              0.6126970600766937
            ]
          },
          {
            "name": "Keo_ve+Ap_sau",
            "coordinates": [
              0.8454697053918844,
              0.6203664252236898,
              0.8999444135630906,
              0.6412441414571793
            ]
          }
        ]
      }
    }
  }
}